nebx/__init__.py
nebx/types.py
nebx/core/ConcurrentTaskManager.py
nebx/core/GeneralUtility.py
nebx/core/ScheduleManager.py
nebx/core/__init__.py
nebx/core/http/HttpHeaderFaker.py
nebx/core/http/RequestWrapperHttpx.py
nebx/core/http/__init__.py
nebx/core/mail/SmtpMailer.py
nebx/core/mail/__init__.py
nebx/interfaces/IConcurrentTaskManager.py
nebx/interfaces/IHttpHeaderFaker.py
nebx/interfaces/IMailer.py
nebx/interfaces/IRequestWrapper.py
nebx/interfaces/__init__.py
nebx-0.2.0.dist-info/METADATA
nebx-0.2.0.dist-info/WHEEL
nebx-0.2.0.dist-info/license.txt
nebx-0.2.0.dist-info/top_level.txt
nebx-0.2.0.dist-info/RECORD
